{"name":"SINCELEJO","deparment_id":"5d558aa8ffbb76528120f30e"}
{"name":"BUENAVISTA","deparment_id":"5d558aa8ffbb76528120f30e"}
{"name":"CAIMITO","deparment_id":"5d558aa8ffbb76528120f30e"}
{"name":"COLOSO","deparment_id":"5d558aa8ffbb76528120f30e"}
{"name":"COROZAL","deparment_id":"5d558aa8ffbb76528120f30e"}
{"name":"COVEÑAS","deparment_id":"5d558aa8ffbb76528120f30e"}
{"name":"CHALAN","deparment_id":"5d558aa8ffbb76528120f30e"}
{"name":"EL ROBLE","deparment_id":"5d558aa8ffbb76528120f30e"}
{"name":"GALERAS","deparment_id":"5d558aa8ffbb76528120f30e"}
{"name":"GUARANDA","deparment_id":"5d558aa8ffbb76528120f30e"}
{"name":"LA UNION","deparment_id":"5d558aa8ffbb76528120f30e"}
{"name":"LOS PALMITOS","deparment_id":"5d558aa8ffbb76528120f30e"}
{"name":"MAJAGUAL","deparment_id":"5d558aa8ffbb76528120f30e"}
{"name":"MORROA","deparment_id":"5d558aa8ffbb76528120f30e"}
{"name":"OVEJAS","deparment_id":"5d558aa8ffbb76528120f30e"}
{"name":"PALMITO","deparment_id":"5d558aa8ffbb76528120f30e"}
{"name":"SAMPUES","deparment_id":"5d558aa8ffbb76528120f30e"}
{"name":"SAN BENITO ABAD","deparment_id":"5d558aa8ffbb76528120f30e"}
{"name":"SAN JUAN DE BETULIA","deparment_id":"5d558aa8ffbb76528120f30e"}
{"name":"SAN MARCOS","deparment_id":"5d558aa8ffbb76528120f30e"}
{"name":"SAN ONOFRE","deparment_id":"5d558aa8ffbb76528120f30e"}
{"name":"SAN PEDRO","deparment_id":"5d558aa8ffbb76528120f30e"}
{"name":"SAN LUIS DE SINCE","deparment_id":"5d558aa8ffbb76528120f30e"}
{"name":"SUCRE","deparment_id":"5d558aa8ffbb76528120f30e"}
{"name":"SANTIAGO DE TOLU","deparment_id":"5d558aa8ffbb76528120f30e"}
{"name":"TOLU VIEJO","deparment_id":"5d558aa8ffbb76528120f30e"}